MANIFEST.in
README.md
setup.cfg
setup.py
django_qcf.egg-info/PKG-INFO
django_qcf.egg-info/SOURCES.txt
django_qcf.egg-info/dependency_links.txt
django_qcf.egg-info/not-zip-safe
django_qcf.egg-info/top_level.txt
qcf/__init__.py
qcf/admin.py
qcf/apps.py
qcf/conf.py
qcf/forms.py
qcf/models.py
qcf/tests.py
qcf/urls.py
qcf/views.py
qcf/locale/fr/LC_MESSAGES/django.mo
qcf/locale/fr/LC_MESSAGES/django.po
qcf/migrations/0001_initial.py
qcf/migrations/0001_initial.pyc
qcf/migrations/__init__.py
qcf/migrations/__init__.pyc
qcf/migrations/__pycache__/0001_initial.cpython-35.pyc
qcf/migrations/__pycache__/__init__.cpython-35.pyc
qcf/templates/qcf/email_form.html
qcf/templates/qcf/form.html
qcf/templates/qcf/ok.html
qcf/templates/qcf/rest_ok.html
qcf/templates/qcf/bootstrap/email_form.html
qcf/templates/qcf/bootstrap/form.html
qcf/templates/qcf/bootstrap/ok.html