Metadata-Version: 1.1
Name: django-qcf
Version: 0.4.2
Summary: Quick contact form for Django
Home-page: https://github.com/synw/django-qcf
Author: synw
Author-email: synwe@yahoo.com
License: UNKNOWN
Download-URL: https://github.com/synw/django-qcf/releases/tag/0.4.2
Keywords: django,contact_form
Platform: UNKNOWN
Classifier: Development Status :: 3 - Alpha
Classifier: Framework :: Django :: 1.9
Classifier: Intended Audience :: Developers
Classifier: License :: OSI Approved :: MIT License
Classifier: Programming Language :: Python :: 2.7
